foliant/preprocessors/apireferences/__init__.py
foliant/preprocessors/apireferences/apireferences.py
foliant/preprocessors/apireferences/classes.py
foliant/preprocessors/apireferences/tools.py
foliantcontrib_apireferences-1.0.9.dist-info/licenses/LICENSE
foliantcontrib_apireferences-1.0.9.dist-info/METADATA
foliantcontrib_apireferences-1.0.9.dist-info/WHEEL
foliantcontrib_apireferences-1.0.9.dist-info/top_level.txt
foliantcontrib_apireferences-1.0.9.dist-info/RECORD
